cmaqsatproc/__init__.py
cmaqsatproc/__main__.py
cmaqsatproc/cmaq.py
cmaqsatproc/utils.py
cmaqsatproc/drivers/__init__.py
cmaqsatproc/drivers/localdisk.py
cmaqsatproc/drivers/opendap.py
cmaqsatproc/drivers/optutils.py
cmaqsatproc/readers/__init__.py
cmaqsatproc/readers/core.py
cmaqsatproc/readers/goes/__init__.py
cmaqsatproc/readers/iasi/__init__.py
cmaqsatproc/readers/modis/__init__.py
cmaqsatproc/readers/modis/modis_readers.py
cmaqsatproc/readers/omi/__init__.py
cmaqsatproc/readers/omps/__init__.py
cmaqsatproc/readers/tropomi/__init__.py
cmaqsatproc/readers/viirs/__init__.py
cmaqsatproc/tests/__init__.py
cmaqsatproc/tests/test_cmaq.py
cmaqsatproc/tests/test_mod04.py
cmaqsatproc/tests/test_omihcho.py
cmaqsatproc/tests/test_omino2.py
cmaqsatproc/tests/test_satellite.py
cmaqsatproc/tests/test_utils.py
cmaqsatproc-0.4.1.dist-info/LICENSE
cmaqsatproc-0.4.1.dist-info/METADATA
cmaqsatproc-0.4.1.dist-info/WHEEL
cmaqsatproc-0.4.1.dist-info/top_level.txt
cmaqsatproc-0.4.1.dist-info/RECORD
