Metadata-Version: 2.1
Name: cmaqsatproc
Version: 0.4.1
Summary: Processor to grid satellite data for comparison to CMAQ.
Home-page: https://github.com/barronh/cmaqsatproc
Author: Barron H. Henderson
Author-email: barronh@gmail.com
Classifier: Programming Language :: Python :: 3
Classifier: License :: OSI Approved :: GNU General Public License v3 (GPLv3)
Classifier: Development Status :: 2 - Pre-Alpha
Classifier: Operating System :: OS Independent
Requires-Python: >=3.6
License-File: LICENSE
Requires-Dist: numpy
Requires-Dist: matplotlib
Requires-Dist: pandas
Requires-Dist: geopandas
Requires-Dist: xarray
Requires-Dist: pyproj
Requires-Dist: shapely
Requires-Dist: pycno
Provides-Extra: gdal
Requires-Dist: gdal ; extra == 'gdal'
